.gitignore
LICENSE.txt
MANIFEST.in
README.rst
setup.py
stdeb.cfg
examples/silly.py
examples/simple.py
motmot/__init__.py
motmot.FastImage.egg-info/PKG-INFO
motmot.FastImage.egg-info/SOURCES.txt
motmot.FastImage.egg-info/dependency_links.txt
motmot.FastImage.egg-info/namespace_packages.txt
motmot.FastImage.egg-info/not-zip-safe
motmot.FastImage.egg-info/top_level.txt
motmot/FastImage/FastImage.c
motmot/FastImage/FastImage.pxd
motmot/FastImage/FastImage.pyx
motmot/FastImage/FastImage_macros.h
motmot/FastImage/__init__.py
motmot/FastImage/tests.py
motmot/FastImage/util.py