Metadata-Version: 1.0
Name: motmot.FastImage
Version: 0.7.0
Summary: Pythonic API for a subset of the Intel Integrated Performance Primitives (Intel IPP) library
Home-page: http://code.astraw.com/projects/motmot
Author: Andrew Straw
Author-email: strawman@astraw.com
License: BSD
Platform: UNKNOWN
